drivecatplus/Global.py
drivecatplus/__init__.py
drivecatplus/drivestats.py
drivecatplus/run_dcp.py
drivecatplus/units.py
drivecatplus-0.2.0.dist-info/METADATA
drivecatplus-0.2.0.dist-info/WHEEL
drivecatplus-0.2.0.dist-info/entry_points.txt
drivecatplus-0.2.0.dist-info/licenses/LICENSE
drivecatplus-0.2.0.dist-info/RECORD
