Metadata-Version: 2.3
Name: drivecatplus
Version: 0.2.0
Summary: NREL's Drive Cycle Analysis Tool Plus
Project-URL: Documentation, https://nrel.github.io/drivecatplus/
Project-URL: Repository, https://github.com/NREL/drivecatplus
Project-URL: Bug Tracker, https://github.com/NREL/drivecatplus/issues
Author-email: Harish Panneer Selvam <Harish.PanneerSelvam@nrel.gov>
Maintainer-email: Harish Panneer Selvam <harish.panneerselvam@nrel.gov>
License-File: LICENSE
Keywords: drivecat,drivecycle,drivecycle-metrics,drivestats,speed-profile,time-speed-trace
Classifier: Development Status :: 4 - Beta
Classifier: Intended Audience :: Developers
Classifier: Intended Audience :: Education
Classifier: Intended Audience :: Science/Research
Classifier: License :: OSI Approved :: BSD License
Classifier: Programming Language :: Python :: 3 :: Only
Classifier: Programming Language :: Python :: 3.8
Classifier: Programming Language :: Python :: 3.9
Classifier: Programming Language :: Python :: 3.10
Classifier: Topic :: Scientific/Engineering
Requires-Python: >=3.8
Requires-Dist: numpy==2.0.0
Requires-Dist: pandas==2.2.2
Requires-Dist: typing-extensions
